CutstomWidgetLoader/CustomWidgetLoaderUpload.py
CutstomWidgetLoader/File_dialog_box.py
CutstomWidgetLoader/__init__.py
Streamlit_Filepath_Loader-0.2.dist-info/METADATA
Streamlit_Filepath_Loader-0.2.dist-info/WHEEL
Streamlit_Filepath_Loader-0.2.dist-info/top_level.txt
Streamlit_Filepath_Loader-0.2.dist-info/RECORD
