Metadata-Version: 2.1
Name: Streamlit-Filepath-Loader
Version: 0.2
Requires-Dist: streamlit==1.39.0
